fast_machine_learning-0.0.2.2.data/data/lib/site-packages/fml/descriptors/dfs/base_descriptor.df
fast_machine_learning-0.0.2.2.data/data/lib/site-packages/fml/descriptors/dfs/ionic_radii.df
fast_machine_learning-0.0.2.2.data/data/lib/site-packages/fml/descriptors/dfs/ionization.df
fast_machine_learning-0.0.2.2.data/data/lib/site-packages/fml/descriptors/dfs/name.df
fast_machine_learning-0.0.2.2.data/data/lib/site-packages/fml/descriptors/dfs/other_descriptor.df
fast_machine_learning-0.0.2.2.data/data/lib/site-packages/fml/descriptors/dfs/str_bool_descriptor.df
fast_machine_learning-0.0.2.2.data/data/lib/site-packages/fml/feature_selection/exec/mrmr
fast_machine_learning-0.0.2.2.data/data/lib/site-packages/fml/feature_selection/exec/mrmr.exe
fml/__init__.py
fml/configs/__init__.py
fml/configs/auto_config.py
fml/configs/pyod_config.py
fml/data/__init__.py
fml/data/dataobject.py
fml/descriptors/__init__.py
fml/descriptors/descriptors.py
fml/ensemble/__init__.py
fml/ensemble/stacking.py
fml/ensemble/voting.py
fml/feature_selection/__init__.py
fml/feature_selection/_shap.py
fml/feature_selection/_utils.py
fml/feature_selection/mrmr.py
fml/formulars/__init__.py
fml/formulars/formular.py
fml/outlier/__init__.py
fml/outlier/outlier.py
fml/parameter_opt/__init__.py
fml/parameter_opt/_utils.py
fml/parameter_opt/gridsearch.py
fml/parameter_opt/hpopt.py
fml/pipelines/__init__.py
fml/pipelines/_utils.py
fml/pipelines/feature_selection_model_fitting.py
fml/pipelines/hpfeature.py
fml/pipelines/hpfeatureparams.py
fml/pipelines/recursive_feature.py
fml/preprocessing/__init__.py
fml/preprocessing/_utils.py
fml/preprocessing/preprocessing.py
fml/sampling/__init__.py
fml/sampling/_utils.py
fml/sampling/hpsplit.py
fml/sampling/sphere_exclusion.py
fml/searching/__init__.py
fml/searching/hts_predicting.py
fml/searching/hyper_searching.py
fml/searching/reverse_projection_hoip.py
fml/targets/__init__.py
fml/targets/target.py
fml/utils/__init__.py
fml/utils/base_class.py
fast_machine_learning-0.0.2.2.dist-info/METADATA
fast_machine_learning-0.0.2.2.dist-info/WHEEL
fast_machine_learning-0.0.2.2.dist-info/top_level.txt
fast_machine_learning-0.0.2.2.dist-info/RECORD
